{
  "json_version": 4,
  "blueprints":
  [
    {
      "name": "blueprint_001",
      "type": "card",
      "layout_size_mm": "60, 40",
      "bleeding_size_mm": "0",
      "main_panel_name": "",
      "hint_order_index": 0,
      "shape_settings":
      {
        "radius_uniform": "False",
        "radius": "5"
      },
      "front_layers":
      [
        {
          "name": "default_front",
          "panels":
          [
            {
              "name": "frame",
              "data":
              {
                "layout_position": "0.000019073, 0",
                "layout_size": "59.99998, 40",
                "panel_type": "image",
                "value": "frame.png",
                "img_sliced": "True",
                "color": "#000000FF"
              }
            },
            {
              "name": "logo",
              "data":
              {
                "layout_position": "22.52472, 6.025123",
                "layout_size": "15.86904, 12.90054",
                "panel_type": "image",
                "value": "logo.png",
                "img_zoom": "0.9556211",
                "visible": "False"
              }
            },
            {
              "name": "text_chinese",
              "data":
              {
                "layout_position": "3.930084, 12.47539",
                "layout_size": "52.13983, 7.573268",
                "layout_constraint_h": "left_and_right",
                "panel_type": "text",
                "value": "中文中文中文中文",
                "text_font": "KaiTi",
                "text_size_max": "30",
                "color": "#000000FF",
                "text_size": "6"
              }
            },
            {
              "name": "text_english",
              "data":
              {
                "layout_position": "8.095505, 21.35083",
                "layout_size": "44.72747, 5.75455",
                "panel_type": "text",
                "value": "English English English",
                "text_alignment_v": "top",
                "text_size": "3.7"
              }
            },
            {
              "name": "bg",
              "data":
              {
                "layout_position": "-1.498253, 0",
                "layout_size": "78.86554, 74.76677",
                "panel_type": "procedural",
                "value": "Text",
                "color": "#FFFFFFFF"
              }
            }
          ]
        }
      ],
      "back_layers":
      [
        {
          "name": "default_back",
          "panels":
          [
            {
              "name": "back_logo",
              "data":
              {
                "layout_size": "60, 40",
                "layout_constraint_h": "left_and_right",
                "layout_constraint_v": "top_and_bottom",
                "panel_type": "image",
                "panel_editable": "False",
                "value": "TC/Logo",
                "img_zoom": "0.75"
              }
            },
            {
              "name": "back_color",
              "data":
              {
                "layout_position": "-25, -25",
                "layout_size": "110, 90.00003",
                "layout_constraint_h": "left_and_right",
                "layout_constraint_v": "top_and_bottom",
                "panel_type": "procedural",
                "panel_editable": "False",
                "color": "#9891FF"
              }
            }
          ]
        }
      ]
    }
  ]
}